[
  {
    "title": "What was the greatest pleasure you ever felt?",
    "url": "https://www.reddit.com/r/AskReddit/comments/p9zjg7/what_was_the_greatest_pleasure_you_ever_felt/",
    "author": "oooliveoil"
  },
  {
    "title": "FDA Approves First COVID-19 Vaccine",
    "url": "https://www.fda.gov/news-events/press-announcements/fda-approves-first-covid-19-vaccine",
    "author": "shabuluba"
  },
  {
    "title": "Percentage of Males who are circumcised in Each country",
    "url": "https://i.redd.it/ij5bedwq52j71.png",
    "author": "sam_3758"
  },
  {
    "title": "FDA grants full approval to Pfizer-BioNTech’s Covid shot, clearing path to more vaccine mandates",
    "url": "https://www.cnbc.com/2021/08/23/fda-pfizer-biontech-covid-vaccine-wins-full-approval-clearing-path-to-mandates.html",
    "author": "s0m3f00l"
  },
  {
    "title": "Don't spill your spaghetti, or you'll be upsetti, here they come, are you ready?",
    "url": "https://i.redd.it/nmwo9eav53j71.jpg",
    "author": "CuddlyCory"
  },
  {
    "title": "The pure joy in his eyes",
    "url": "https://v.redd.it/u43t0wddu3j71",
    "author": "Bmchris44"
  },
  {
    "title": "American guy being detained for wearing Russian flag t-shirt in Odessa, Ukraine",
    "url": "https://v.redd.it/np04uqsv93j71",
    "author": "formerclimber"
  },
  {
    "title": "This piglet and his private fireplace",
    "url": "https://v.redd.it/24jea3df54j71",
    "author": "V_y_z_n_v"
  },
  {
    "title": "When you die of COVID and this is the profile pic you left",
    "url": "https://www.reddit.com/gallery/p9q2v0",
    "author": "katkrystal"
  },
  {
    "title": "Can you imagine the right-wing outrage if Biden did this?!",
    "url": "https://i.redd.it/wtmkkyyj74j71.jpg",
    "author": "TROLOLOL6969"
  },
  {
    "title": "I hate the weird ending for nard dog",
    "url": "https://i.redd.it/yyyvg0rcb3j71.jpg",
    "author": "Tharknight"
  },
  {
    "title": "Kissed by a train",
    "url": "https://v.redd.it/8737ck3d51j71",
    "author": "Sif_Thor"
  },
  {
    "title": "I designed and printed a working Simpsons TV. Plays the first 11 seasons at random without internet. Knobs work too!",
    "url": "https://v.redd.it/12qcrcsf8zi71",
    "author": "buba447"
  },
  {
    "title": "The tongue twister",
    "url": "https://v.redd.it/t911imlz82j71",
    "author": "Think_Tax5749"
  },
  {
    "title": "Pro Players actively supporting being a shitty teammate.",
    "url": "https://i.redd.it/b79jsvu7j2j71.jpg",
    "author": "Antonite7"
  },
  {
    "title": "What are your biggest Switch related regrets? Shameful stories, regrettable purchases, lapse of judgement?",
    "url": "https://www.reddit.com/r/NintendoSwitch/comments/p9vz1o/what_are_your_biggest_switch_related_regrets/",
    "author": "Ivanqula"
  },
  {
    "title": "Looks perfect to me",
    "url": "https://i.redd.it/8pgfgg2g54j71.jpg",
    "author": "deadstar420"
  },
  {
    "title": "This might be the best wedding photo ever",
    "url": "https://i.redd.it/4d4h2kzlz3j71.jpg",
    "author": "ohnoh18"
  },
  {
    "title": "Right-Wing Dems Begin to Cave as Progressives Hold Their Ground on Reconciliation Vote",
    "url": "https://www.commondreams.org/news/2021/08/23/right-wing-dems-begin-cave-progressives-hold-their-ground-reconciliation-vote",
    "author": "morenewsat11"
  },
  {
    "title": "This is *supposed* to be a statue of the Virgin Mary from a sculptor named Maria Scanu",
    "url": "https://i.redd.it/59pugn2l72j71.jpg",
    "author": "bendubberley_"
  },
  {
    "title": "TIFU by telling my wife what she is out of 10.",
    "url": "https://www.reddit.com/r/tifu/comments/p9pto9/tifu_by_telling_my_wife_what_she_is_out_of_10/",
    "author": "goagro"
  },
  {
    "title": "Girl talks about being “dreamsexual” and everyone is just silent",
    "url": "https://v.redd.it/3vrbgx53b1j71",
    "author": "Warden206"
  },
  {
    "title": "FDA grants Pfizer COVID-19 vaccine full approval",
    "url": "https://www.foxbusiness.com/healthcare/fda-grants-pfizer-covid-19-vaccine-full-approval#",
    "author": "f1sh98"
  },
  {
    "title": "Tell your kids you love them.",
    "url": "https://i.redd.it/3r4lnq8u53j71.jpg",
    "author": "esberat"
  },
  {
    "title": "Feeling like leisure is wasteful and unproductive may lead to less happiness and higher levels of stress and depression, new research suggests (Four studies, n = 1310)",
    "url": "https://news.osu.edu/think-leisure-is-a-waste-that-may-not-bode-well-for-your-mental-health/",
    "author": "geoff199"
  }
]